MANIFEST.in
README.md
setup.py
xapdbclib/HandleDbByPydbclib.py
xapdbclib/__init__.py
xapdbclib.egg-info/PKG-INFO
xapdbclib.egg-info/SOURCES.txt
xapdbclib.egg-info/dependency_links.txt
xapdbclib.egg-info/requires.txt
xapdbclib.egg-info/top_level.txt
xapdbclib/pydbclib/__init__.py
xapdbclib/pydbclib/database.py
xapdbclib/pydbclib/drivers.py
xapdbclib/pydbclib/exceptions.py
xapdbclib/pydbclib/record.py
xapdbclib/pydbclib/sql.py
xapdbclib/pydbclib/utils.py