Metadata-Version: 1.0
Name: xapdbclib
Version: 1.0
Summary: XAP系统---数据库读取和存储python版
Home-page: https://github.com/lanwajing/xapdbclib
Author: xuanbin
Author-email: 1454240159@qq.com
License: MIT Licence
Keywords: pip,license,licensetool,tool,gm
Platform: any
